README.md
pyproject.toml
setup.cfg
setup.py
simcm.py
simcm.egg-info/PKG-INFO
simcm.egg-info/SOURCES.txt
simcm.egg-info/dependency_links.txt
simcm.egg-info/requires.txt
simcm.egg-info/top_level.txt
test/test_simcm.py