Metadata-Version: 2.1
Name: simcm
Version: 2.0.1
Summary: Use this tool to develop unit tests which obtain complete coverage.
Home-page: https://github.com/paulwexler/simcm
Author: Paul Wexler
Author-email: paul.e.wexler@gmail.com
License: MIT
Keywords: simulate,unittest,mock,development
Platform: UNKNOWN
Classifier: Intended Audience :: Developers
Classifier: Topic :: Software Development :: Testing :: Mocking
Classifier: Topic :: Software Development :: Testing :: Unit
Classifier: License :: OSI Approved :: MIT License
Classifier: Programming Language :: Python :: 3
Provides-Extra: dev
Provides-Extra: test
